{
  "names": {
    "aaron": ["아론", "에런", "애런"],
    "adam": ["아담"],
    "adrian": ["아드리안", "에이드리언"],
    "aidan": ["에이든"],
    "alan": ["앨런", "알란"],
    "alex": ["알렉스"],
    "alexander": ["알렉산더"],
    "alexandra": ["알렉산드라"],
    "alexandria": ["알렉산드리아"],
    "alexa": ["알렉사"],
    "alexis": ["알렉시스"],
    "alicia": ["알리시아"],
    "allison": ["앨리슨"],
    "alyssa": ["알리사"],
    "amanda": ["아만다"],
    "amber": ["앰버"],
    "amelia": ["아멜리아"],
    "amy": ["에이미"],
    "andrea": ["안드레아"],
    "andrew": ["앤드류"],
    "angel": ["안젤"],
    "angela": ["안젤라"],
    "angelina": ["안젤리나"],
    "anna": ["안나", "애나"],
    "anthony": ["앤서니", "안토니"],
    "antonio": ["안토니오"],
    "ariana": ["아리아나"],
    "ashley": ["애슐리"],
    "audrey": ["오드리"],
    "austin": ["오스틴"],
    "autumn": ["오텀"],
    "ava": ["에이바"],
    "avery": ["에이버리"],
    "bailey": ["베일리"],
    "barbara": ["바바라"],
    "benjamin": ["벤자민"],
    "betty": ["베티"],
    "blake": ["블레이크"],
    "bradley": ["브래들리"],
    "brandon": ["브랜든"],
    "brayden": ["브레이든"],
    "breanna": ["브리애나"],
    "brenda": ["브렌다"],
    "brian": ["브라이언"],
    "brianna": ["브리애나"],
    "briana": ["브리애나"],
    "brittany": ["브리트니"],
    "brooke": ["브룩"],
    "brooklyn": ["브루클린"],
    "bryan": ["브라이언"],
    "caitlin": ["케이틀린"],
    "caleb": ["케일럽"],
    "cameron": ["카메론"],
    "carlos": ["카를로스"],
    "carol": ["캐롤"],
    "caroline": ["캐롤라인"],
    "carson": ["카슨"],
    "carter": ["카터"],
    "cassandra": ["카산드라"],
    "catherine": ["캐서린"],
    "charles": ["찰스"],
    "chase": ["체이스"],
    "chelsea": ["첼시"],
    "cheyenne": ["샤이엔"],
    "chloe": ["클로이"],
    "chris": ["크리스"],
    "christian": ["크리스천"],
    "christina": ["크리스티나"],
    "christine": ["크리스틴"],
    "christopher": ["크리스토퍼"],
    "claire": ["클레어"],
    "cody": ["코디"],
    "cole": ["콜"],
    "connor": ["코너"],
    "corey": ["코리"],
    "courtney": ["코트니"],
    "crystal": ["크리스털"],
    "cynthia": ["신시아"],
    "dakota": ["다코타"],
    "daniel": ["다니엘"],
    "danielle": ["다니엘"],
    "david": ["데이비드"],
    "deborah": ["데보라"],
    "derek": ["데렉"],
    "destiny": ["데스티니"],
    "devin": ["데빈"],
    "diana": ["다이애나"],
    "diego": ["디에고"],
    "dominic": ["도미닉"],
    "donna": ["도나"],
    "dorothy": ["도로시"],
    "dustin": ["더스틴"],
    "dylan": ["딜런"],
    "edward": ["에드워드"],
    "elijah": ["일라이자"],
    "elizabeth": ["엘리자베스"],
    "ella": ["엘라"],
    "emily": ["에밀리"],
    "emma": ["에마", "엠마"],
    "eric": ["에릭"],
    "erica": ["에리카"],
    "erin": ["에린"],
    "ethan": ["이든"],
    "evan": ["에반"],
    "evelyn": ["에블린"],
    "faith": ["페이스"],
    "gabriel": ["가브리엘"],
    "gabrielle": ["가브리엘"],
    "gabriella": ["가브리엘라"],
    "garrett": ["개릿"],
    "gavin": ["개빈"],
    "grace": ["그레이스"],
    "gregory": ["그레고리"],
    "hailey": ["헤일리"],
    "haley": ["헤일리"],
    "hannah": ["한나"],
    "hayden": ["헤이든"],
    "heather": ["헤더"],
    "helen": ["헬렌"],
    "hunter": ["헌터"],
    "ian": ["이언"],
    "isaac": ["이삭"],
    "isabel": ["이사벨"],
    "isabella": ["이사벨라"],
    "isaiah": ["이사야"],
    "jada": ["제이다"],
    "jaden": ["제이든"],
    "jack": ["잭"],
    "jackson": ["잭슨"],
    "jacob": ["제이콥"],
    "jacqueline": ["재클린"],
    "james": ["제임스"],
    "jamie": ["제이미"],
    "jane": ["제인"],
    "jared": ["재러드"],
    "jason": ["제이슨"],
    "jasmine": ["재스민"],
    "jayden": ["제이든"],
    "jeffrey": ["제프리"],
    "jenna": ["제나"],
    "jennifer": ["제니퍼"],
    "jeremy": ["제레미"],
    "jeremiah": ["제러마이어"],
    "jesse": ["제시"],
    "jessica": ["제시카"],
    "jesus": ["헤수스"],
    "joan": ["조안"],
    "jocelyn": ["조슬린"],
    "john": ["존"],
    "jonathan": ["조나단", "조너선"],
    "jordan": ["조던"],
    "joseph": ["조셉"],
    "joshua": ["조슈아"],
    "juan": ["후안"],
    "judith": ["주디스"],
    "judy": ["주디"],
    "julia": ["줄리아"],
    "julian": ["줄리안"],
    "julie": ["줄리"],
    "justin": ["저스틴"],
    "kaitlyn": ["케이틀린"],
    "karen": ["카렌"],
    "katherine": ["캐서린"],
    "kathryn": ["캐스린"],
    "katelyn": ["케이틀린"],
    "kathy": ["캐시"],
    "katie": ["케이티"],
    "kayla": ["케일라"],
    "kaylee": ["케일리"],
    "kelly": ["켈리"],
    "kelsey": ["켈시"],
    "kenneth": ["케네스"],
    "kevin": ["케빈"],
    "kimberly": ["킴벌리"],
    "kristen": ["크리스텐"],
    "kyle": ["카일"],
    "kylie": ["카일리"],
    "landon": ["랜든"],
    "laura": ["로라"],
    "lauren": ["로렌"],
    "leah": ["리아"],
    "liam": ["리암"],
    "lily": ["릴리"],
    "lillian": ["릴리안"],
    "linda": ["린다"],
    "lindsey": ["린지"],
    "lisa": ["리사"],
    "logan": ["로건"],
    "lori": ["로리"],
    "lucas": ["루카스"],
    "luis": ["루이스"],
    "luke": ["루크"],
    "mackenzie": ["맥켄지"],
    "madeline": ["매들린"],
    "madison": ["매디슨"],
    "makayla": ["마케일라"],
    "margaret": ["마가렛"],
    "mariah": ["마라이어"],
    "maria": ["마리아"],
    "marie": ["마리"],
    "marilyn": ["마릴린"],
    "marissa": ["마리사"],
    "mark": ["마크"],
    "marcus": ["마커스"],
    "martha": ["마사"],
    "martin": ["마틴"],
    "mary": ["메리"],
    "mason": ["메이슨"],
    "matthew": ["매튜"],
    "maya": ["마야"],
    "megan": ["메간"],
    "melanie": ["멜라니"],
    "melissa": ["멜리사"],
    "mia": ["미아"],
    "michael": ["마이클"],
    "michelle": ["미셸"],
    "miguel": ["미구엘"],
    "miranda": ["미란다"],
    "mitchell": ["미첼"],
    "molly": ["몰리"],
    "monica": ["모니카"],
    "morgan": ["모건"],
    "nancy": ["낸시"],
    "natalie": ["나탈리"],
    "nathan": ["네이선"],
    "nathaniel": ["나다니엘"],
    "nevaeh": ["네바"],
    "nicholas": ["니콜라스"],
    "nicole": ["니콜"],
    "noah": ["노아"],
    "olivia": ["올리비아"],
    "owen": ["오웬"],
    "paige": ["페이지"],
    "pamela": ["파멜라"],
    "patrick": ["패트릭"],
    "paul": ["폴"],
    "peter": ["피터"],
    "rachel": ["레이첼"],
    "rebecca": ["레베카"],
    "richard": ["리처드"],
    "riley": ["라일리"],
    "robert": ["로버트"],
    "ruth": ["루스"],
    "ryan": ["라이언"],
    "sabrina": ["사브리나"],
    "samantha": ["사만다"],
    "samuel": ["사무엘", "새뮤얼"],
    "sandra": ["산드라"],
    "sara": ["사라"],
    "sarah": ["사라"],
    "savannah": ["사바나"],
    "scott": ["스콧"],
    "sean": ["숀"],
    "sebastian": ["세바스티안"],
    "seth": ["세스"],
    "shane": ["셰인"],
    "shannon": ["섀넌"],
    "sharon": ["샤론"],
    "shawn": ["숀"],
    "shelby": ["셸비"],
    "sierra": ["시에라"],
    "sofia": ["소피아"],
    "sophia": ["소피아"],
    "spencer": ["스펜서"],
    "stephen": ["스티븐"],
    "stephanie": ["스테파니"],
    "steven": ["스티븐"],
    "susan": ["수잔"],
    "sydney": ["시드니"],
    "taylor": ["테일러"],
    "teresa": ["테레사"],
    "theresa": ["테레사"],
    "thomas": ["토마스"],
    "tiffany": ["티파니"],
    "timothy": ["티모시"],
    "travis": ["트래비스"],
    "trevor": ["트레버"],
    "trinity": ["트리니티"],
    "tristan": ["트리스탄"],
    "tyler": ["타일러"],
    "vanessa": ["바네사"],
    "victor": ["빅터"],
    "victoria": ["빅토리아"],
    "virginia": ["버지니아"],
    "wendy": ["웬디"],
    "whitney": ["휘트니"],
    "william": ["윌리엄"],
    "wyatt": ["와이어트"],
    "xavier": ["자비에르"],
    "zachary": ["재커리"],
    "zoe": ["조이"],
    "aaliyah": ["알리야"],
    "addison": ["애디슨"],
    "abigail": ["애비게일"],
    "jose": ["호세"]
  }
}
